{
    "language": "english",
    "type": "standard",
    "era": "1000-500bc",
    "version": "3.0",
    "template_version": "3.0",
    "event_id": 2002,
    "parent_id": null,
    "granularity": "detailed",
    "content_hash": "sha256:5c92e0db8e22558516b517a5a6f394d3f57b300401278633f5da0c7b7545a5e4",
    "summary": "The Sack of Hao (Haojing, 771 BC) by the Quanrong nomads was one of the pivotal events in Chinese history — the destruction of the Western Zhou capital near modern Xi'an that ended the Western Zhou dynasty and forced the royal court's relocation eastward to Luoyi (modern Luoyang), inaugurating the Eastern Zhou period (Spring and Autumn and Warring States). King You of Zhou was killed in the attack, and the surviving Zhou nobility installed his son Ping as king at the eastern capital.\n\nThe political consequences were enormous: the Zhou royal house never recovered its genuine military and political authority. While the Zhou kings retained their ritual and symbolic role as the nominal center of Chinese civilization — the 'Son of Heaven' whose sacrifices maintained cosmic order — actual power devolved to the feudal lords (zhuhou) of the many Zhou states. The [[event:1953|Zhou Dynasty Spring Autumn]] period that followed was one of sophisticated interstate diplomacy and cultural achievement, but of fundamental Zhou royal weakness. The sack and relocation is thus the Chinese equivalent of Rome's sack by the Gauls (390 BC) in its symbolic impact — a traumatic rupture that ended a golden age and began a new, more complex era of competing powers.",
    "wikipedia_url": "https://en.wikipedia.org/wiki/Sack_of_Hao",
    "read_more_links": [
        {
            "title": "King You of Zhou fall",
            "url": "https://en.wikipedia.org/wiki/King_You_of_Zhou"
        },
        {
            "title": "Eastern Zhou beginning",
            "url": "https://en.wikipedia.org/wiki/Eastern_Zhou"
        },
        {
            "title": "Quanrong nomadic people",
            "url": "https://en.wikipedia.org/wiki/Quanrong"
        }
    ],
    "images": [],
    "figures": [],
    "territory_geojson": null
}