{
    "language": "english",
    "type": "standard",
    "era": "1900-2000ad",
    "version": "3.0",
    "template_version": "3.0",
    "event_id": 2744,
    "parent_id": null,
    "granularity": "detailed",
    "content_hash": "sha256:d24000c7a5cb7e051f93154c698fe32f7d6f37e7f28ee73268e643b52defd482",
    "summary": "The second wave of feminism emerged in the United States and spread across Western countries during the 1960s and 1970s, building on the first wave's achievements in securing women's suffrage to address a broader range of issues including workplace discrimination, reproductive rights, domestic violence, and the cultural subordination of women. Betty Friedan's 1963 book The Feminine Mystique, which challenged the assumption that domestic life was naturally fulfilling for women, is often identified as a catalytic text. The National Organization for Women was founded in 1966, providing organizational infrastructure for legislative and legal campaigns.\n\nSecond-wave feminism achieved major legal changes in the United States, including Title IX of the Education Amendments of 1972 (which prohibited sex discrimination in federally funded education programs), the Equal Employment Opportunity Act, and the landmark Roe v. Wade Supreme Court decision in 1973 that established a constitutional right to abortion. In the United Kingdom and other Western European countries, similar legislative reforms expanded women's rights in employment, divorce, and reproductive health. Feminist activists simultaneously challenged cultural representations of women and pushed for changes in language, education, and professional norms.\n\nThe movement generated enduring debates about strategy, priorities, and the diversity of women's experiences. Critics from within feminism noted that second-wave campaigns were often led by and primarily benefited white, middle-class women, failing to adequately address the intersecting burdens of race and class faced by women of color. These critiques contributed to subsequent theoretical developments including intersectionality, which became influential in academic feminist thought from the 1980s onward.",
    "wikipedia_url": "https://en.wikipedia.org/wiki/Second-wave_feminism",
    "read_more_links": [
        {
            "title": "Feminism - Encyclopaedia Britannica",
            "url": "https://www.britannica.com/topic/feminism"
        },
        {
            "title": "Betty Friedan - Wikipedia",
            "url": "https://en.wikipedia.org/wiki/Betty_Friedan"
        },
        {
            "title": "Title IX - Wikipedia",
            "url": "https://en.wikipedia.org/wiki/Title_IX"
        }
    ],
    "images": [],
    "figures": [],
    "territory_geojson": null
}