{
    "language": "english",
    "type": "standard",
    "era": "1900-2000ad",
    "version": "3.0",
    "template_version": "3.0",
    "event_id": 3359,
    "parent_id": 2676,
    "granularity": "notable",
    "content_hash": "sha256:2e55870aa1c12fac90198ed45ceb5633f9965a0cf1b7df0e94fd6b962e0c7d61",
    "summary": "On April 12, 1961, Soviet cosmonaut Yuri Gagarin became the first human being to travel to outer space and orbit the Earth. Launched aboard the Vostok 1 spacecraft from the Baikonur Cosmodrome in Kazakhstan, Gagarin completed a single orbit of the Earth in 108 minutes before re-entering the atmosphere and parachuting to a safe landing in the Soviet Union. His calm radio transmissions and reported observation that the Earth appeared as a pale blue sphere became among the most celebrated moments of the twentieth century.\n\nGagarin's flight was the culmination of the Soviet space program's rapid development under chief designer Sergei Korolev, operating under intense secrecy. The achievement shocked the United States, which had lost the satellite race to Sputnik in 1957 and now found itself falling behind in the manned spaceflight competition. President Kennedy responded by announcing the goal of landing Americans on the Moon before the end of the decade — a commitment that produced the Apollo program.\n\nGagarin himself became an international celebrity of extraordinary magnitude, touring the world to thunderous receptions. He never flew in space again; Soviet authorities considered him too valuable as a symbol to risk in further missions. He died in a training aircraft crash in 1968. His flight inaugurated the era of human spaceflight and transformed the [[event:2676|Space Race]] into its most dramatic phase, as both superpowers committed vast resources to establishing human presence beyond Earth's atmosphere.",
    "wikipedia_url": "https://en.wikipedia.org/wiki/Yuri_Gagarin",
    "read_more_links": [
        {
            "title": "Vostok 1 - Wikipedia",
            "url": "https://en.wikipedia.org/wiki/Vostok_1"
        },
        {
            "title": "Space Race - Encyclopaedia Britannica",
            "url": "https://www.britannica.com/topic/space-race"
        },
        {
            "title": "Soviet Space Program - Wikipedia",
            "url": "https://en.wikipedia.org/wiki/Soviet_space_program"
        }
    ],
    "images": [],
    "figures": [],
    "territory_geojson": null
}