{
    "language": "english",
    "type": "standard",
    "era": "500-1bc",
    "version": "3.0",
    "template_version": "3.0",
    "event_id": 1240,
    "parent_id": null,
    "granularity": "detailed",
    "content_hash": "sha256:3fc044bacfbe169d75ee60b1dff4ff29201b41ee46e5c55119bb572eae1f39ab",
    "summary": "The circumnavigation of Africa by Phoenician sailors (c. 600 BC) is reported by Herodotus as having been commissioned by the Egyptian pharaoh Necho II. According to Herodotus, Phoenician sailors departed from the Red Sea, sailed south and around Africa, and returned through the Pillars of Hercules (Strait of Gibraltar) to Egypt after approximately three years. The account includes a detail Herodotus himself found unbelievable — that the sun was on the sailors' right hand (north) as they sailed westward around the southern tip of Africa — which modern analysts consider evidence that the event actually occurred, since this is precisely what one would observe south of the equator.\n\nNo Phoenician records of this voyage survive independently, and debate continues about its historicity. If genuine, it would represent the first known circumnavigation of Africa by approximately 2,100 years, preceding Vasco da Gama's 1497–1499 voyage. The voyage would have required exceptional navigational skill and endurance, including stopping to grow crops on shore to resupply. The Phoenicians' maritime expertise — they were the dominant Mediterranean seafarers of their era, reaching Britain and West Africa on other recorded voyages — makes the account at least plausible.",
    "wikipedia_url": "https://en.wikipedia.org/wiki/Hanno_the_Navigator",
    "read_more_links": [
        {
            "title": "Necho II pharaoh",
            "url": "https://en.wikipedia.org/wiki/Necho_II"
        },
        {
            "title": "Herodotus account of circumnavigation",
            "url": "https://en.wikipedia.org/wiki/Phoenician_circumnavigation_of_Africa"
        },
        {
            "title": "Phoenician exploration",
            "url": "https://en.wikipedia.org/wiki/Phoenicia#Trade_and_exploration"
        }
    ],
    "images": [],
    "figures": [],
    "territory_geojson": null
}